molabel/__init__.py
molabel/image.py
molabel/widget.py
molabel/static/image-widget.css
molabel/static/image-widget.js
molabel/static/widget.css
molabel/static/widget.js
molabel-0.1.5.dist-info/METADATA
molabel-0.1.5.dist-info/WHEEL
molabel-0.1.5.dist-info/RECORD
