Metadata-Version: 2.4
Name: molabel
Version: 0.1.5
Summary: A simple annotation widget for labeling examples
Author-email: Your Name <your.email@example.com>
Requires-Python: >=3.8
Requires-Dist: anywidget>=0.9.0
Requires-Dist: traitlets>=5.0.0
Provides-Extra: dev
Requires-Dist: black>=22.0; extra == 'dev'
Requires-Dist: pytest>=7.0; extra == 'dev'
Requires-Dist: ruff>=0.0.270; extra == 'dev'
Provides-Extra: images
Requires-Dist: numpy>=1.20.0; extra == 'images'
Requires-Dist: pillow>=9.0.0; extra == 'images'
